pyexpander/__init__.py
pyexpander/expander.py
pyexpander/lib.py
pyexpander/msi2pyexpander.py
pyexpander/parser.py
pyexpander/doc/LICENSE
pyexpander/doc/README.rst
pyexpander/doc/html/epics-support.html
pyexpander/doc/html/expander-options.html
pyexpander/doc/html/genindex.html
pyexpander/doc/html/index.html
pyexpander/doc/html/introduction.html
pyexpander/doc/html/license.html
pyexpander/doc/html/msi2pyexpander-options.html
pyexpander/doc/html/objects.inv
pyexpander/doc/html/py-modindex.html
pyexpander/doc/html/pyexpander-install.html
pyexpander/doc/html/python3.html
pyexpander/doc/html/reference-expander.html
pyexpander/doc/html/search.html
pyexpander/doc/html/searchindex.js
pyexpander/doc/html/source-code-documentation.html
pyexpander/doc/html/_images/logo_hzb_big.png
pyexpander/doc/html/_modules/expander.html
pyexpander/doc/html/_modules/index.html
pyexpander/doc/html/_modules/pyexpander/lib.html
pyexpander/doc/html/_modules/pyexpander/parser.html
pyexpander/doc/html/_sources/epics-support.rst.txt
pyexpander/doc/html/_sources/expander-options.rst.txt
pyexpander/doc/html/_sources/index.rst.txt
pyexpander/doc/html/_sources/introduction.rst.txt
pyexpander/doc/html/_sources/license.rst.txt
pyexpander/doc/html/_sources/msi2pyexpander-options.rst.txt
pyexpander/doc/html/_sources/pyexpander-install.rst.txt
pyexpander/doc/html/_sources/python3.rst.txt
pyexpander/doc/html/_sources/reference-expander.rst.txt
pyexpander/doc/html/_sources/source-code-documentation.rst.txt
pyexpander/doc/html/_static/_sphinx_javascript_frameworks_compat.js
pyexpander/doc/html/_static/basic.css
pyexpander/doc/html/_static/doctools.js
pyexpander/doc/html/_static/documentation_options.js
pyexpander/doc/html/_static/file.png
pyexpander/doc/html/_static/jquery.js
pyexpander/doc/html/_static/language_data.js
pyexpander/doc/html/_static/minus.png
pyexpander/doc/html/_static/plus.png
pyexpander/doc/html/_static/pygments.css
pyexpander/doc/html/_static/searchtools.js
pyexpander-2.2.2.dist-info/licenses/LICENSE
pyexpander-2.2.2.dist-info/METADATA
pyexpander-2.2.2.dist-info/WHEEL
pyexpander-2.2.2.dist-info/entry_points.txt
pyexpander-2.2.2.dist-info/top_level.txt
pyexpander-2.2.2.dist-info/RECORD
